easysnmp/__init__.py
easysnmp/compat.py
easysnmp/easy.py
easysnmp/exceptions.py
easysnmp/helpers.py
easysnmp/interface.cpython-310-x86_64-linux-gnu.so
easysnmp/session.py
easysnmp/utils.py
easysnmp/variables.py
chturne_easysnmp-0.2.5.dist-info/LICENSE
chturne_easysnmp-0.2.5.dist-info/METADATA
chturne_easysnmp-0.2.5.dist-info/WHEEL
chturne_easysnmp-0.2.5.dist-info/top_level.txt
chturne_easysnmp-0.2.5.dist-info/RECORD
