Metadata-Version: 2.1
Name: chturne-easysnmp
Version: 0.2.5
Summary: A blazingly fast and Pythonic SNMP library based on the official Net-SNMP bindings
Home-page: https://github.com/kamakazikamikaze/easysnmp
Author: Kent Coble
Author-email: coblekent@gmail.com
License: BSD
Platform: UNKNOWN
Classifier: Development Status :: 4 - Beta
Classifier: Intended Audience :: Developers
Classifier: License :: OSI Approved :: BSD License
Classifier: Operating System :: OS Independent
Classifier: Programming Language :: Python
Classifier: Programming Language :: Python :: 2.6
Classifier: Programming Language :: Python :: 2.7
Classifier: Programming Language :: Python :: 3.3
Classifier: Programming Language :: Python :: 3.4
Classifier: Programming Language :: Python :: 3.5
Classifier: Programming Language :: Python :: 3.6
Classifier: Topic :: System :: Networking
Classifier: Topic :: System :: Networking :: Monitoring
License-File: LICENSE
